vmmsetup/__init__.py
vmmsetup/vmmsetup.py
vmmsetup-0.1.0.dist-info/METADATA
vmmsetup-0.1.0.dist-info/WHEEL
vmmsetup-0.1.0.dist-info/RECORD
