Metadata-Version: 2.1
Name: vmmsetup
Version: 0.1.0
Summary: Reads the env PROJECT_ROOT, and adds it to sys path. In this way, you can execute your python file from nested project structures.
Author: vmm-mmv
Author-email: mihai.vieru@isa.utm.md
Requires-Python: >=3.10,<4.0
Classifier: Programming Language :: Python :: 3
Classifier: Programming Language :: Python :: 3.10
Classifier: Programming Language :: Python :: 3.11
Classifier: Programming Language :: Python :: 3.12
Classifier: Programming Language :: Python :: 3.13
Requires-Dist: python-dotenv (>=1.0.1,<2.0.0)
